README.md
setup.py
RBAPG/__help__.py
RBAPG/__init__.py
RBAPG/__main__.py
RBAPG.egg-info/PKG-INFO
RBAPG.egg-info/SOURCES.txt
RBAPG.egg-info/dependency_links.txt
RBAPG.egg-info/top_level.txt